LICENSE
README
setup.py
oosapy/__init__.py
oosapy/api.py
oosapy/auth.py
oosapy/error.py
oosapy/models.py
oosapy/oauth.py
oosapy.egg-info/PKG-INFO
oosapy.egg-info/SOURCES.txt
oosapy.egg-info/dependency_links.txt
oosapy.egg-info/requires.txt
oosapy.egg-info/top_level.txt
oosapy.egg-info/zip-safe
samples/__init__.py
samples/api_read_example.py
samples/api_search_example.py
samples/api_update_example.py
samples/command_line_test.py
samples/user_authorization.py