Metadata-Version: 1.0
Name: oosapy
Version: 0.1.1
Summary: 11870.com v2 API library for python
Home-page: http://code.google.com/p/oosapy/
Author: 11870.com
Author-email: api-11870@googlegroups.com
License: Apache License, Version 2.0
Keywords: 11870.com library
Platform: UNKNOWN
Classifier: Development Status :: 4 - Beta
Classifier: Programming Language :: Python
Classifier: Topic :: Software Development :: Libraries :: Python Modules
